pandas_degreedays/__init__.py
pandas_degreedays/version.py
pandas_degreedays/provider/__init__.py
pandas_degreedays/provider/base.py
pandas_degreedays/provider/openweathermap.py
pandas_degreedays-0.0.6.dist-info/DESCRIPTION.rst
pandas_degreedays-0.0.6.dist-info/entry_points.txt
pandas_degreedays-0.0.6.dist-info/METADATA
pandas_degreedays-0.0.6.dist-info/metadata.json
pandas_degreedays-0.0.6.dist-info/RECORD
pandas_degreedays-0.0.6.dist-info/top_level.txt
pandas_degreedays-0.0.6.dist-info/WHEEL
