Metadata-Version: 2.0
Name: pandas-degreedays
Version: 0.0.6
Summary: Pandas degree days
Home-page: https://github.com/scls19fr/pandas_degreedays
Author: Sebastien Celles
Author-email: s.celles@gmail.com
License: BSD
Keywords: pandas data weather temperature degree days
Platform: UNKNOWN
Classifier: Development Status :: 3 - Alpha
Classifier: Environment :: Console
Classifier: Intended Audience :: Science/Research
Classifier: Operating System :: OS Independent
Classifier: Programming Language :: Cython
Classifier: Programming Language :: Python
Classifier: Programming Language :: Python :: 2.7
Classifier: Programming Language :: Python :: 3.3
Classifier: Programming Language :: Python :: 3.4
Classifier: Topic :: Scientific/Engineering
Classifier: License :: OSI Approved :: BSD License
Requires-Dist: pandas
Requires-Dist: six
Provides-Extra: dev
Requires-Dist: check-manifest; extra == 'dev'
Requires-Dist: nose; extra == 'dev'
Provides-Extra: test
Requires-Dist: coverage; extra == 'test'
Requires-Dist: nose; extra == 'test'
